setup.py
gagar/__init__.py
gagar/draw_background.py
gagar/draw_cells.py
gagar/draw_hud.py
gagar/drawutils.py
gagar/main.py
gagar/reload.py
gagar/skins.py
gagar/subscriber.py
gagar/window.py
gagar.egg-info/PKG-INFO
gagar.egg-info/SOURCES.txt
gagar.egg-info/dependency_links.txt
gagar.egg-info/entry_points.txt
gagar.egg-info/requires.txt
gagar.egg-info/top_level.txt